{
  "data": {
    "1": {
      "sources": [
        1
      ],
      "dage": 68,
      "matches": [
        {
          "recipient": 5,
          "score": 74
        },
        {
          "recipient": 16,
          "score": 21
        },
        {
          "recipient": 19,
          "score": 19
        },
        {
          "recipient": 27,
          "score": 4
        },
        {
          "recipient": 37,
          "score": 10
        },
        {
          "recipient": 38,
          "score": 26
        },
        {
          "recipient": 42,
          "score": 64
        },
        {
          "recipient": 44,
          "score": 70
        },
        {
          "recipient": 49,
          "score": 87
        },
        {
          "recipient": 61,
          "score": 41
        },
        {
          "recipient": 68,
          "score": 8
        },
        {
          "recipient": 71,
          "score": 49
        },
        {
          "recipient": 78,
          "score": 74
        },
        {
          "recipient": 80,
          "score": 66
        },
        {
          "recipient": 82,
          "score": 56
        },
        {
          "recipient": 89,
          "score": 68
        },
        {
          "recipient": 90,
          "score": 48
        },
        {
          "recipient": 91,
          "score": 73
        },
        {
          "recipient": 103,
          "score": 17
        },
        {
          "recipient": 109,
          "score": 32
        }
      ]
    },
    "2": {
      "sources": [
        2
      ],
      "dage": 26,
      "matches": [
        {
          "recipient": 16,
          "score": 54
        },
        {
          "recipient": 24,
          "score": 70
        },
        {
          "recipient": 61,
          "score": 82
        },
        {
          "recipient": 68,
          "score": 60
        },
        {
          "recipient": 97,
          "score": 58
        },
        {
          "recipient": 104,
          "score": 56
        }
      ]
    },
    "3": {
      "sources": [
        3
      ],
      "dage": 37
    },
    "5": {
      "sources": [
        5
      ],
      "dage": 25,
      "matches": [
        {
          "recipient": 16,
          "score": 70
        },
        {
          "recipient": 24,
          "score": 53
        },
        {
          "recipient": 27,
          "score": 88
        },
        {
          "recipient": 36,
          "score": 64
        },
        {
          "recipient": 38,
          "score": 20
        },
        {
          "recipient": 45,
          "score": 5
        },
        {
          "recipient": 53,
          "score": 2
        },
        {
          "recipient": 61,
          "score": 19
        },
        {
          "recipient": 67,
          "score": 24
        },
        {
          "recipient": 68,
          "score": 49
        },
        {
          "recipient": 71,
          "score": 13
        },
        {
          "recipient": 80,
          "score": 1
        },
        {
          "recipient": 81,
          "score": 17
        },
        {
          "recipient": 89,
          "score": 34
        },
        {
          "recipient": 90,
          "score": 16
        },
        {
          "recipient": 103,
          "score": 6
        },
        {
          "recipient": 104,
          "score": 78
        }
      ]
    },
    "6": {
      "sources": [
        6
      ],
      "dage": 24,
      "matches": [
        {
          "recipient": 16,
          "score": 47
        },
        {
          "recipient": 27,
          "score": 60
        },
        {
          "recipient": 61,
          "score": 40
        },
        {
          "recipient": 68,
          "score": 88
        },
        {
          "recipient": 99,
          "score": 88
        },
        {
          "recipient": 104,
          "score": 81
        }
      ]
    },
    "7": {
      "sources": [
        7
      ],
      "dage": 68
    },
    "8": {
      "sources": [
        8
      ],
      "dage": 30,
      "matches": [
        {
          "recipient": 2,
          "score": 21
        },
        {
          "recipient": 9,
          "score": 50
        },
        {
          "recipient": 16,
          "score": 55
        },
        {
          "recipient": 18,
          "score": 19
        },
        {
          "recipient": 27,
          "score": 60
        },
        {
          "recipient": 28,
          "score": 36
        },
        {
          "recipient": 31,
          "score": 13
        },
        {
          "recipient": 38,
          "score": 29
        },
        {
          "recipient": 48,
          "score": 83
        },
        {
          "recipient": 53,
          "score": 40
        },
        {
          "recipient": 55,
          "score": 83
        },
        {
          "recipient": 61,
          "score": 67
        },
        {
          "recipient": 68,
          "score": 87
        },
        {
          "recipient": 69,
          "score": 8
        },
        {
          "recipient": 71,
          "score": 50
        },
        {
          "recipient": 80,
          "score": 49
        },
        {
          "recipient": 89,
          "score": 14
        },
        {
          "recipient": 90,
          "score": 66
        },
        {
          "recipient": 97,
          "score": 89
        },
        {
          "recipient": 104,
          "score": 54
        },
        {
          "recipient": 108,
          "score": 36
        },
        {
          "recipient": 111,
          "score": 15
        }
      ]
    },
    "9": {
      "sources": [
        9
      ],
      "dage": 66,
      "matches": [
        {
          "recipient": 16,
          "score": 61
        },
        {
          "recipient": 27,
          "score": 29
        },
        {
          "recipient": 32,
          "score": 1
        },
        {
          "recipient": 38,
          "score": 10
        },
        {
          "recipient": 48,
          "score": 52
        },
        {
          "recipient": 51,
          "score": 68
        },
        {
          "recipient": 53,
          "score": 85
        },
        {
          "recipient": 65,
          "score": 71
        },
        {
          "recipient": 68,
          "score": 2
        },
        {
          "recipient": 69,
          "score": 71
        },
        {
          "recipient": 71,
          "score": 14
        },
        {
          "recipient": 75,
          "score": 89
        },
        {
          "recipient": 80,
          "score": 66
        },
        {
          "recipient": 83,
          "score": 28
        },
        {
          "recipient": 86,
          "score": 63
        },
        {
          "recipient": 87,
          "score": 53
        },
        {
          "recipient": 89,
          "score": 20
        },
        {
          "recipient": 90,
          "score": 23
        },
        {
          "recipient": 92,
          "score": 28
        },
        {
          "recipient": 104,
          "score": 77
        },
        {
          "recipient": 106,
          "score": 55
        }
      ]
    },
    "10": {
      "sources": [
        10
      ],
      "dage": 62,
      "matches": [
        {
          "recipient": 16,
          "score": 2
        },
        {
          "recipient": 23,
          "score": 22
        },
        {
          "recipient": 26,
          "score": 58
        },
        {
          "recipient": 27,
          "score": 11
        },
        {
          "recipient": 38,
          "score": 66
        },
        {
          "recipient": 53,
          "score": 46
        },
        {
          "recipient": 61,
          "score": 34
        },
        {
          "recipient": 68,
          "score": 72
        },
        {
          "recipient": 71,
          "score": 1
        },
        {
          "recipient": 75,
          "score": 87
        },
        {
          "recipient": 80,
          "score": 68
        },
        {
          "recipient": 89,
          "score": 33
        },
        {
          "recipient": 90,
          "score": 80
        },
        {
          "recipient": 97,
          "score": 68
        },
        {
          "recipient": 100,
          "score": 4
        },
        {
          "recipient": 104,
          "score": 16
        }
      ]
    },
    "12": {
      "sources": [
        12
      ],
      "dage": 51,
      "matches": [
        {
          "recipient": 16,
          "score": 41
        },
        {
          "recipient": 26,
          "score": 77
        },
        {
          "recipient": 27,
          "score": 37
        },
        {
          "recipient": 61,
          "score": 86
        },
        {
          "recipient": 68,
          "score": 9
        },
        {
          "recipient": 103,
          "score": 30
        },
        {
          "recipient": 104,
          "score": 50
        }
      ]
    },
    "14": {
      "sources": [
        14
      ],
      "dage": 50,
      "matches": [
        {
          "recipient": 16,
          "score": 7
        },
        {
          "recipient": 23,
          "score": 59
        },
        {
          "recipient": 27,
          "score": 44
        },
        {
          "recipient": 61,
          "score": 73
        },
        {
          "recipient": 68,
          "score": 23
        },
        {
          "recipient": 104,
          "score": 35
        }
      ]
    },
    "16": {
      "sources": [
        16
      ],
      "dage": 35
    },
    "17": {
      "sources": [
        17
      ],
      "dage": 53,
      "matches": [
        {
          "recipient": 16,
          "score": 8
        },
        {
          "recipient": 21,
          "score": 52
        },
        {
          "recipient": 24,
          "score": 75
        },
        {
          "recipient": 27,
          "score": 62
        },
        {
          "recipient": 28,
          "score": 61
        },
        {
          "recipient": 32,
          "score": 15
        },
        {
          "recipient": 38,
          "score": 40
        },
        {
          "recipient": 50,
          "score": 1
        },
        {
          "recipient": 53,
          "score": 54
        },
        {
          "recipient": 56,
          "score": 6
        },
        {
          "recipient": 60,
          "score": 27
        },
        {
          "recipient": 61,
          "score": 60
        },
        {
          "recipient": 65,
          "score": 22
        },
        {
          "recipient": 66,
          "score": 3
        },
        {
          "recipient": 71,
          "score": 2
        },
        {
          "recipient": 80,
          "score": 1
        },
        {
          "recipient": 89,
          "score": 45
        },
        {
          "recipient": 90,
          "score": 53
        },
        {
          "recipient": 91,
          "score": 47
        },
        {
          "recipient": 101,
          "score": 25
        },
        {
          "recipient": 104,
          "score": 43
        }
      ]
    },
    "18": {
      "sources": [
        18
      ],
      "dage": 66,
      "matches": [
        {
          "recipient": 16,
          "score": 88
        },
        {
          "recipient": 20,
          "score": 1
        },
        {
          "recipient": 27,
          "score": 71
        },
        {
          "recipient": 61,
          "score": 19
        },
        {
          "recipient": 77,
          "score": 51
        },
        {
          "recipient": 103,
          "score": 35
        },
        {
          "recipient": 104,
          "score": 47
        },
        {
          "recipient": 106,
          "score": 67
        }
      ]
    },
    "19": {
      "sources": [
        19
      ],
      "dage": 35,
      "matches": [
        {
          "recipient": 1,
          "score": 31
        },
        {
          "recipient": 16,
          "score": 50
        },
        {
          "recipient": 26,
          "score": 36
        },
        {
          "recipient": 27,
          "score": 61
        },
        {
          "recipient": 28,
          "score": 66
        },
        {
          "recipient": 33,
          "score": 8
        },
        {
          "recipient": 38,
          "score": 38
        },
        {
          "recipient": 53,
          "score": 0
        },
        {
          "recipient": 56,
          "score": 57
        },
        {
          "recipient": 61,
          "score": 66
        },
        {
          "recipient": 66,
          "score": 50
        },
        {
          "recipient": 68,
          "score": 56
        },
        {
          "recipient": 71,
          "score": 87
        },
        {
          "recipient": 75,
          "score": 12
        },
        {
          "recipient": 76,
          "score": 64
        },
        {
          "recipient": 80,
          "score": 55
        },
        {
          "recipient": 87,
          "score": 29
        },
        {
          "recipient": 89,
          "score": 84
        },
        {
          "recipient": 97,
          "score": 66
        },
        {
          "recipient": 100,
          "score": 28
        }
      ]
    },
    "20": {
      "sources": [
        20
      ],
      "dage": 52,
      "matches": [
        {
          "recipient": 16,
          "score": 19
        },
        {
          "recipient": 27,
          "score": 6
        },
        {
          "recipient": 28,
          "score": 25
        },
        {
          "recipient": 54,
          "score": 31
        },
        {
          "recipient": 61,
          "score": 26
        },
        {
          "recipient": 62,
          "score": 69
        },
        {
          "recipient": 68,
          "score": 11
        },
        {
          "recipient": 99,
          "score": 72
        },
        {
          "recipient": 103,
          "score": 13
        },
        {
          "recipient": 104,
          "score": 39
        }
      ]
    },
    "21": {
      "sources": [
        21
      ],
      "dage": 38,
      "matches": [
        {
          "recipient": 3,
          "score": 42
        },
        {
          "recipient": 16,
          "score": 70
        },
        {
          "recipient": 23,
          "score": 19
        },
        {
          "recipient": 27,
          "score": 6
        },
        {
          "recipient": 61,
          "score": 20
        },
        {
          "recipient": 68,
          "score": 52
        },
        {
          "recipient": 92,
          "score": 75
        },
        {
          "recipient": 97,
          "score": 33
        },
        {
          "recipient": 99,
          "score": 37
        },
        {
          "recipient": 104,
          "score": 61
        }
      ]
    },
    "23": {
      "sources": [
        23
      ],
      "dage": 21,
      "matches": [
        {
          "recipient": 10,
          "score": 77
        },
        {
          "recipient": 16,
          "score": 51
        },
        {
          "recipient": 24,
          "score": 40
        },
        {
          "recipient": 27,
          "score": 75
        },
        {
          "recipient": 61,
          "score": 44
        },
        {
          "recipient": 68,
          "score": 85
        },
        {
          "recipient": 104,
          "score": 34
        }
      ]
    },
    "24": {
      "sources": [
        24
      ],
      "dage": 31,
      "matches": [
        {
          "recipient": 16,
          "score": 32
        },
        {
          "recipient": 20,
          "score": 41
        },
        {
          "recipient": 27,
          "score": 77
        },
        {
          "recipient": 61,
          "score": 24
        },
        {
          "recipient": 68,
          "score": 47
        }
      ]
    },
    "25": {
      "sources": [
        25
      ],
      "dage": 66,
      "matches": [
        {
          "recipient": 16,
          "score": 30
        },
        {
          "recipient": 26,
          "score": 59
        },
        {
          "recipient": 27,
          "score": 66
        },
        {
          "recipient": 68,
          "score": 71
        },
        {
          "recipient": 104,
          "score": 79
        }
      ]
    },
    "26": {
      "sources": [
        26
      ],
      "dage": 28,
      "matches": [
        {
          "recipient": 3,
          "score": 5
        },
        {
          "recipient": 16,
          "score": 57
        },
        {
          "recipient": 27,
          "score": 12
        },
        {
          "recipient": 38,
          "score": 29
        },
        {
          "recipient": 51,
          "score": 51
        },
        {
          "recipient": 53,
          "score": 52
        },
        {
          "recipient": 61,
          "score": 16
        },
        {
          "recipient": 64,
          "score": 66
        },
        {
          "recipient": 68,
          "score": 7
        },
        {
          "recipient": 71,
          "score": 50
        },
        {
          "recipient": 82,
          "score": 88
        },
        {
          "recipient": 89,
          "score": 22
        },
        {
          "recipient": 90,
          "score": 46
        },
        {
          "recipient": 96,
          "score": 8
        },
        {
          "recipient": 104,
          "score": 11
        },
        {
          "recipient": 109,
          "score": 31
        }
      ]
    },
    "27": {
      "sources": [
        27
      ],
      "dage": 33,
      "matches": [
        {
          "recipient": 3,
          "score": 61
        },
        {
          "recipient": 8,
          "score": 7
        },
        {
          "recipient": 16,
          "score": 59
        },
        {
          "recipient": 24,
          "score": 63
        },
        {
          "recipient": 43,
          "score": 50
        },
        {
          "recipient": 54,
          "score": 28
        },
        {
          "recipient": 61,
          "score": 74
        },
        {
          "recipient": 68,
          "score": 60
        },
        {
          "recipient": 92,
          "score": 84
        },
        {
          "recipient": 99,
          "score": 12
        },
        {
          "recipient": 104,
          "score": 29
        }
      ]
    },
    "28": {
      "sources": [
        28
      ],
      "dage": 56,
      "matches": [
        {
          "recipient": 1,
          "score": 86
        },
        {
          "recipient": 9,
          "score": 31
        },
        {
          "recipient": 16,
          "score": 3
        },
        {
          "recipient": 24,
          "score": 40
        },
        {
          "recipient": 27,
          "score": 88
        },
        {
          "recipient": 38,
          "score": 79
        },
        {
          "recipient": 39,
          "score": 39
        },
        {
          "recipient": 49,
          "score": 55
        },
        {
          "recipient": 51,
          "score": 18
        },
        {
          "recipient": 53,
          "score": 85
        },
        {
          "recipient": 54,
          "score": 11
        },
        {
          "recipient": 61,
          "score": 35
        },
        {
          "recipient": 68,
          "score": 36
        },
        {
          "recipient": 71,
          "score": 88
        },
        {
          "recipient": 73,
          "score": 64
        },
        {
          "recipient": 74,
          "score": 14
        },
        {
          "recipient": 80,
          "score": 52
        },
        {
          "recipient": 89,
          "score": 67
        },
        {
          "recipient": 90,
          "score": 78
        },
        {
          "recipient": 99,
          "score": 27
        },
        {
          "recipient": 104,
          "score": 42
        },
        {
          "recipient": 109,
          "score": 55
        }
      ]
    },
    "29": {
      "sources": [
        29
      ],
      "dage": 63,
      "matches": [
        {
          "recipient": 16,
          "score": 70
        },
        {
          "recipient": 27,
          "score": 45
        },
        {
          "recipient": 61,
          "score": 2
        },
        {
          "recipient": 68,
          "score": 72
        },
        {
          "recipient": 77,
          "score": 59
        },
        {
          "recipient": 103,
          "score": 40
        },
        {
          "recipient": 104,
          "score": 58
        }
      ]
    },
    "31": {
      "sources": [
        31
      ],
      "dage": 20,
      "matches": [
        {
          "recipient": 10,
          "score": 19
        },
        {
          "recipient": 16,
          "score": 74
        },
        {
          "recipient": 27,
          "score": 55
        },
        {
          "recipient": 61,
          "score": 31
        },
        {
          "recipient": 68,
          "score": 77
        },
        {
          "recipient": 77,
          "score": 59
        },
        {
          "recipient": 103,
          "score": 5
        },
        {
          "recipient": 104,
          "score": 4
        }
      ]
    },
    "32": {
      "sources": [
        32
      ],
      "dage": 46,
      "matches": [
        {
          "recipient": 5,
          "score": 79
        },
        {
          "recipient": 14,
          "score": 16
        },
        {
          "recipient": 16,
          "score": 0
        },
        {
          "recipient": 23,
          "score": 67
        },
        {
          "recipient": 27,
          "score": 34
        },
        {
          "recipient": 38,
          "score": 50
        },
        {
          "recipient": 53,
          "score": 84
        },
        {
          "recipient": 54,
          "score": 58
        },
        {
          "recipient": 61,
          "score": 63
        },
        {
          "recipient": 68,
          "score": 1
        },
        {
          "recipient": 71,
          "score": 52
        },
        {
          "recipient": 80,
          "score": 32
        },
        {
          "recipient": 82,
          "score": 31
        },
        {
          "recipient": 89,
          "score": 52
        },
        {
          "recipient": 90,
          "score": 80
        },
        {
          "recipient": 97,
          "score": 41
        },
        {
          "recipient": 104,
          "score": 42
        }
      ]
    },
    "33": {
      "sources": [
        33
      ],
      "dage": 55,
      "matches": [
        {
          "recipient": 16,
          "score": 74
        },
        {
          "recipient": 23,
          "score": 79
        },
        {
          "recipient": 27,
          "score": 5
        },
        {
          "recipient": 34,
          "score": 82
        },
        {
          "recipient": 37,
          "score": 42
        },
        {
          "recipient": 68,
          "score": 64
        },
        {
          "recipient": 104,
          "score": 23
        }
      ]
    },
    "34": {
      "sources": [
        34
      ],
      "dage": 64,
      "matches": [
        {
          "recipient": 1,
          "score": 86
        },
        {
          "recipient": 2,
          "score": 54
        },
        {
          "recipient": 16,
          "score": 49
        },
        {
          "recipient": 25,
          "score": 58
        },
        {
          "recipient": 27,
          "score": 75
        },
        {
          "recipient": 38,
          "score": 9
        },
        {
          "recipient": 47,
          "score": 37
        },
        {
          "recipient": 51,
          "score": 78
        },
        {
          "recipient": 52,
          "score": 15
        },
        {
          "recipient": 53,
          "score": 59
        },
        {
          "recipient": 61,
          "score": 52
        },
        {
          "recipient": 65,
          "score": 43
        },
        {
          "recipient": 71,
          "score": 34
        },
        {
          "recipient": 74,
          "score": 23
        },
        {
          "recipient": 89,
          "score": 56
        },
        {
          "recipient": 90,
          "score": 17
        },
        {
          "recipient": 104,
          "score": 86
        }
      ]
    },
    "36": {
      "sources": [
        36
      ],
      "dage": 44,
      "matches": [
        {
          "recipient": 10,
          "score": 68
        },
        {
          "recipient": 16,
          "score": 2
        },
        {
          "recipient": 27,
          "score": 54
        },
        {
          "recipient": 54,
          "score": 15
        },
        {
          "recipient": 61,
          "score": 17
        },
        {
          "recipient": 67,
          "score": 12
        },
        {
          "recipient": 68,
          "score": 57
        },
        {
          "recipient": 77,
          "score": 85
        },
        {
          "recipient": 104,
          "score": 24
        }
      ]
    },
    "37": {
      "sources": [
        37
      ],
      "dage": 39,
      "matches": [
        {
          "recipient": 16,
          "score": 10
        },
        {
          "recipient": 18,
          "score": 87
        },
        {
          "recipient": 27,
          "score": 47
        },
        {
          "recipient": 29,
          "score": 20
        },
        {
          "recipient": 38,
          "score": 75
        },
        {
          "recipient": 52,
          "score": 83
        },
        {
          "recipient": 53,
          "score": 10
        },
        {
          "recipient": 54,
          "score": 68
        },
        {
          "recipient": 55,
          "score": 30
        },
        {
          "recipient": 60,
          "score": 53
        },
        {
          "recipient": 61,
          "score": 20
        },
        {
          "recipient": 68,
          "score": 34
        },
        {
          "recipient": 71,
          "score": 88
        },
        {
          "recipient": 76,
          "score": 75
        },
        {
          "recipient": 80,
          "score": 32
        },
        {
          "recipient": 89,
          "score": 46
        },
        {
          "recipient": 90,
          "score": 73
        },
        {
          "recipient": 102,
          "score": 87
        },
        {
          "recipient": 104,
          "score": 51
        },
        {
          "recipient": 111,
          "score": 10
        }
      ]
    },
    "38": {
      "sources": [
        38
      ],
      "dage": 65,
      "matches": [
        {
          "recipient": 18,
          "score": 19
        },
        {
          "recipient": 78,
          "score": 51
        }
      ]
    },
    "39": {
      "sources": [
        39
      ],
      "dage": 33,
      "matches": [
        {
          "recipient": 16,
          "score": 19
        },
        {
          "recipient": 27,
          "score": 74
        },
        {
          "recipient": 34,
          "score": 38
        },
        {
          "recipient": 61,
          "score": 74
        },
        {
          "recipient": 68,
          "score": 73
        },
        {
          "recipient": 77,
          "score": 11
        },
        {
          "recipient": 93,
          "score": 14
        },
        {
          "recipient": 102,
          "score": 81
        },
        {
          "recipient": 104,
          "score": 60
        }
      ]
    },
    "40": {
      "sources": [
        40
      ],
      "dage": 53,
      "matches": [
        {
          "recipient": 3,
          "score": 13
        },
        {
          "recipient": 27,
          "score": 73
        },
        {
          "recipient": 61,
          "score": 19
        },
        {
          "recipient": 68,
          "score": 71
        },
        {
          "recipient": 104,
          "score": 77
        }
      ]
    },
    "42": {
      "sources": [
        42
      ],
      "dage": 51,
      "matches": [
        {
          "recipient": 16,
          "score": 74
        },
        {
          "recipient": 27,
          "score": 1
        },
        {
          "recipient": 61,
          "score": 0
        },
        {
          "recipient": 68,
          "score": 5
        },
        {
          "recipient": 99,
          "score": 68
        },
        {
          "recipient": 104,
          "score": 25
        }
      ]
    },
    "43": {
      "sources": [
        43
      ],
      "dage": 53,
      "matches": [
        {
          "recipient": 8,
          "score": 53
        },
        {
          "recipient": 16,
          "score": 16
        },
        {
          "recipient": 27,
          "score": 30
        },
        {
          "recipient": 68,
          "score": 67
        },
        {
          "recipient": 92,
          "score": 52
        },
        {
          "recipient": 104,
          "score": 81
        }
      ]
    },
    "44": {
      "sources": [
        44
      ],
      "dage": 50,
      "matches": [
        {
          "recipient": 18,
          "score": 69
        },
        {
          "recipient": 53,
          "score": 43
        }
      ]
    },
    "45": {
      "sources": [
        45
      ],
      "dage": 36,
      "matches": [
        {
          "recipient": 5,
          "score": 33
        },
        {
          "recipient": 6,
          "score": 11
        },
        {
          "recipient": 12,
          "score": 29
        },
        {
          "recipient": 16,
          "score": 6
        },
        {
          "recipient": 38,
          "score": 54
        },
        {
          "recipient": 48,
          "score": 13
        },
        {
          "recipient": 53,
          "score": 63
        },
        {
          "recipient": 59,
          "score": 28
        },
        {
          "recipient": 61,
          "score": 52
        },
        {
          "recipient": 68,
          "score": 63
        },
        {
          "recipient": 71,
          "score": 16
        },
        {
          "recipient": 77,
          "score": 48
        },
        {
          "recipient": 80,
          "score": 70
        },
        {
          "recipient": 89,
          "score": 51
        },
        {
          "recipient": 90,
          "score": 22
        },
        {
          "recipient": 92,
          "score": 84
        },
        {
          "recipient": 104,
          "score": 47
        },
        {
          "recipient": 106,
          "score": 15
        },
        {
          "recipient": 108,
          "score": 76
        }
      ]
    },
    "46": {
      "sources": [
        46
      ],
      "dage": 52,
      "matches": [
        {
          "recipient": 10,
          "score": 66
        },
        {
          "recipient": 16,
          "score": 40
        },
        {
          "recipient": 27,
          "score": 17
        },
        {
          "recipient": 34,
          "score": 7
        },
        {
          "recipient": 37,
          "score": 86
        },
        {
          "recipient": 61,
          "score": 83
        },
        {
          "recipient": 62,
          "score": 22
        },
        {
          "recipient": 67,
          "score": 17
        },
        {
          "recipient": 68,
          "score": 39
        },
        {
          "recipient": 93,
          "score": 42
        },
        {
          "recipient": 104,
          "score": 68
        }
      ]
    },
    "47": {
      "sources": [
        47
      ],
      "dage": 26,
      "matches": [
        {
          "recipient": 1,
          "score": 66
        },
        {
          "recipient": 16,
          "score": 74
        },
        {
          "recipient": 23,
          "score": 59
        },
        {
          "recipient": 27,
          "score": 46
        },
        {
          "recipient": 68,
          "score": 61
        },
        {
          "recipient": 79,
          "score": 70
        },
        {
          "recipient": 97,
          "score": 46
        },
        {
          "recipient": 104,
          "score": 76
        },
        {
          "recipient": 105,
          "score": 5
        }
      ]
    },
    "48": {
      "sources": [
        48
      ],
      "dage": 62,
      "matches": [
        {
          "recipient": 10,
          "score": 30
        },
        {
          "recipient": 16,
          "score": 65
        },
        {
          "recipient": 20,
          "score": 37
        },
        {
          "recipient": 25,
          "score": 12
        },
        {
          "recipient": 27,
          "score": 84
        },
        {
          "recipient": 28,
          "score": 3
        },
        {
          "recipient": 33,
          "score": 51
        },
        {
          "recipient": 38,
          "score": 86
        },
        {
          "recipient": 39,
          "score": 53
        },
        {
          "recipient": 53,
          "score": 40
        },
        {
          "recipient": 61,
          "score": 65
        },
        {
          "recipient": 68,
          "score": 60
        },
        {
          "recipient": 69,
          "score": 78
        },
        {
          "recipient": 71,
          "score": 19
        },
        {
          "recipient": 81,
          "score": 29
        },
        {
          "recipient": 82,
          "score": 30
        },
        {
          "recipient": 89,
          "score": 75
        },
        {
          "recipient": 90,
          "score": 48
        },
        {
          "recipient": 94,
          "score": 25
        },
        {
          "recipient": 104,
          "score": 20
        }
      ]
    },
    "49": {
      "sources": [
        49
      ],
      "dage": 67,
      "matches": [
        {
          "recipient": 20,
          "score": 5
        },
        {
          "recipient": 27,
          "score": 9
        },
        {
          "recipient": 61,
          "score": 85
        },
        {
          "recipient": 68,
          "score": 67
        },
        {
          "recipient": 97,
          "score": 23
        },
        {
          "recipient": 104,
          "score": 70
        }
      ]
    },
    "50": {
      "sources": [
        50
      ],
      "dage": 62,
      "matches": [
        {
          "recipient": 16,
          "score": 20
        },
        {
          "recipient": 21,
          "score": 89
        },
        {
          "recipient": 33,
          "score": 75
        },
        {
          "recipient": 38,
          "score": 22
        },
        {
          "recipient": 40,
          "score": 12
        },
        {
          "recipient": 42,
          "score": 69
        },
        {
          "recipient": 53,
          "score": 88
        },
        {
          "recipient": 61,
          "score": 56
        },
        {
          "recipient": 70,
          "score": 44
        },
        {
          "recipient": 71,
          "score": 3
        },
        {
          "recipient": 74,
          "score": 59
        },
        {
          "recipient": 80,
          "score": 78
        },
        {
          "recipient": 81,
          "score": 86
        },
        {
          "recipient": 86,
          "score": 44
        },
        {
          "recipient": 89,
          "score": 80
        },
        {
          "recipient": 90,
          "score": 10
        },
        {
          "recipient": 93,
          "score": 9
        },
        {
          "recipient": 100,
          "score": 30
        },
        {
          "recipient": 104,
          "score": 36
        }
      ]
    },
    "51": {
      "sources": [
        51
      ],
      "dage": 28,
      "matches": [
        {
          "recipient": 16,
          "score": 76
        },
        {
          "recipient": 27,
          "score": 5
        },
        {
          "recipient": 37,
          "score": 17
        },
        {
          "recipient": 43,
          "score": 64
        },
        {
          "recipient": 68,
          "score": 56
        },
        {
          "recipient": 92,
          "score": 8
        },
        {
          "recipient": 104,
          "score": 24
        }
      ]
    },
    "52": {
      "sources": [
        52
      ],
      "dage": 61,
      "matches": [
        {
          "recipient": 6,
          "score": 55
        },
        {
          "recipient": 16,
          "score": 68
        },
        {
          "recipient": 21,
          "score": 20
        },
        {
          "recipient": 27,
          "score": 63
        },
        {
          "recipient": 29,
          "score": 46
        },
        {
          "recipient": 39,
          "score": 78
        },
        {
          "recipient": 45,
          "score": 28
        },
        {
          "recipient": 53,
          "score": 29
        },
        {
          "recipient": 61,
          "score": 39
        },
        {
          "recipient": 68,
          "score": 55
        },
        {
          "recipient": 71,
          "score": 77
        },
        {
          "recipient": 80,
          "score": 12
        },
        {
          "recipient": 89,
          "score": 59
        },
        {
          "recipient": 90,
          "score": 76
        },
        {
          "recipient": 100,
          "score": 76
        },
        {
          "recipient": 104,
          "score": 52
        },
        {
          "recipient": 105,
          "score": 9
        }
      ]
    },
    "53": {
      "sources": [
        53
      ],
      "dage": 43,
      "matches": [
        {
          "recipient": 16,
          "score": 45
        },
        {
          "recipient": 25,
          "score": 52
        },
        {
          "recipient": 27,
          "score": 64
        },
        {
          "recipient": 38,
          "score": 30
        },
        {
          "recipient": 49,
          "score": 52
        },
        {
          "recipient": 57,
          "score": 35
        },
        {
          "recipient": 61,
          "score": 50
        },
        {
          "recipient": 63,
          "score": 40
        },
        {
          "recipient": 64,
          "score": 17
        },
        {
          "recipient": 66,
          "score": 73
        },
        {
          "recipient": 68,
          "score": 83
        },
        {
          "recipient": 71,
          "score": 49
        },
        {
          "recipient": 80,
          "score": 40
        },
        {
          "recipient": 82,
          "score": 77
        },
        {
          "recipient": 90,
          "score": 77
        },
        {
          "recipient": 99,
          "score": 51
        },
        {
          "recipient": 100,
          "score": 84
        },
        {
          "recipient": 104,
          "score": 58
        },
        {
          "recipient": 105,
          "score": 89
        },
        {
          "recipient": 108,
          "score": 55
        }
      ]
    },
    "54": {
      "sources": [
        54
      ],
      "dage": 60,
      "matches": [
        {
          "recipient": 1,
          "score": 48
        },
        {
          "recipient": 16,
          "score": 5
        },
        {
          "recipient": 24,
          "score": 16
        },
        {
          "recipient": 27,
          "score": 1
        },
        {
          "recipient": 61,
          "score": 46
        },
        {
          "recipient": 68,
          "score": 58
        },
        {
          "recipient": 77,
          "score": 65
        },
        {
          "recipient": 104,
          "score": 84
        }
      ]
    },
    "55": {
      "sources": [
        55
      ],
      "dage": 62,
      "matches": [
        {
          "recipient": 61,
          "score": 8
        },
        {
          "recipient": 68,
          "score": 55
        },
        {
          "recipient": 92,
          "score": 73
        },
        {
          "recipient": 104,
          "score": 49
        },
        {
          "recipient": 105,
          "score": 16
        },
        {
          "recipient": 106,
          "score": 13
        }
      ]
    },
    "56": {
      "sources": [
        56
      ],
      "dage": 33,
      "matches": [
        {
          "recipient": 3,
          "score": 28
        },
        {
          "recipient": 8,
          "score": 85
        },
        {
          "recipient": 16,
          "score": 54
        },
        {
          "recipient": 27,
          "score": 77
        },
        {
          "recipient": 61,
          "score": 1
        },
        {
          "recipient": 68,
          "score": 25
        },
        {
          "recipient": 106,
          "score": 59
        }
      ]
    },
    "57": {
      "sources": [
        57
      ],
      "dage": 32,
      "matches": [
        {
          "recipient": 10,
          "score": 79
        },
        {
          "recipient": 16,
          "score": 16
        },
        {
          "recipient": 27,
          "score": 51
        },
        {
          "recipient": 28,
          "score": 42
        },
        {
          "recipient": 61,
          "score": 66
        },
        {
          "recipient": 62,
          "score": 42
        },
        {
          "recipient": 68,
          "score": 57
        },
        {
          "recipient": 79,
          "score": 40
        },
        {
          "recipient": 104,
          "score": 18
        }
      ]
    },
    "58": {
      "sources": [
        58
      ],
      "dage": 24,
      "matches": [
        {
          "recipient": 16,
          "score": 75
        },
        {
          "recipient": 27,
          "score": 13
        },
        {
          "recipient": 34,
          "score": 89
        },
        {
          "recipient": 61,
          "score": 62
        },
        {
          "recipient": 68,
          "score": 43
        },
        {
          "recipient": 103,
          "score": 21
        },
        {
          "recipient": 105,
          "score": 88
        },
        {
          "recipient": 106,
          "score": 25
        }
      ]
    },
    "59": {
      "sources": [
        59
      ],
      "dage": 57,
      "matches": [
        {
          "recipient": 53,
          "score": 58
        }
      ]
    },
    "60": {
      "sources": [
        60
      ],
      "dage": 39,
      "matches": [
        {
          "recipient": 16,
          "score": 13
        },
        {
          "recipient": 27,
          "score": 17
        },
        {
          "recipient": 46,
          "score": 79
        },
        {
          "recipient": 48,
          "score": 53
        },
        {
          "recipient": 50,
          "score": 76
        },
        {
          "recipient": 53,
          "score": 62
        },
        {
          "recipient": 61,
          "score": 24
        },
        {
          "recipient": 68,
          "score": 57
        },
        {
          "recipient": 71,
          "score": 38
        },
        {
          "recipient": 76,
          "score": 3
        },
        {
          "recipient": 80,
          "score": 18
        },
        {
          "recipient": 87,
          "score": 69
        },
        {
          "recipient": 90,
          "score": 52
        },
        {
          "recipient": 96,
          "score": 9
        },
        {
          "recipient": 104,
          "score": 38
        }
      ]
    },
    "61": {
      "sources": [
        61
      ],
      "dage": 51,
      "matches": [
        {
          "recipient": 16,
          "score": 24
        },
        {
          "recipient": 27,
          "score": 79
        },
        {
          "recipient": 68,
          "score": 31
        },
        {
          "recipient": 104,
          "score": 23
        }
      ]
    },
    "62": {
      "sources": [
        62
      ],
      "dage": 20,
      "matches": [
        {
          "recipient": 3,
          "score": 81
        },
        {
          "recipient": 16,
          "score": 52
        },
        {
          "recipient": 27,
          "score": 87
        },
        {
          "recipient": 28,
          "score": 66
        },
        {
          "recipient": 34,
          "score": 11
        },
        {
          "recipient": 61,
          "score": 71
        },
        {
          "recipient": 68,
          "score": 19
        },
        {
          "recipient": 79,
          "score": 34
        },
        {
          "recipient": 104,
          "score": 12
        }
      ]
    },
    "63": {
      "sources": [
        63
      ],
      "dage": 55,
      "matches": [
        {
          "recipient": 102,
          "score": 17
        }
      ]
    },
    "64": {
      "sources": [
        64
      ],
      "dage": 40,
      "matches": [
        {
          "recipient": 7,
          "score": 51
        },
        {
          "recipient": 16,
          "score": 54
        },
        {
          "recipient": 18,
          "score": 56
        },
        {
          "recipient": 24,
          "score": 42
        },
        {
          "recipient": 27,
          "score": 87
        },
        {
          "recipient": 37,
          "score": 70
        },
        {
          "recipient": 38,
          "score": 77
        },
        {
          "recipient": 45,
          "score": 21
        },
        {
          "recipient": 46,
          "score": 12
        },
        {
          "recipient": 49,
          "score": 83
        },
        {
          "recipient": 50,
          "score": 26
        },
        {
          "recipient": 53,
          "score": 42
        },
        {
          "recipient": 54,
          "score": 8
        },
        {
          "recipient": 55,
          "score": 27
        },
        {
          "recipient": 59,
          "score": 64
        },
        {
          "recipient": 61,
          "score": 15
        },
        {
          "recipient": 68,
          "score": 39
        },
        {
          "recipient": 71,
          "score": 11
        },
        {
          "recipient": 73,
          "score": 18
        },
        {
          "recipient": 80,
          "score": 55
        },
        {
          "recipient": 89,
          "score": 86
        },
        {
          "recipient": 90,
          "score": 50
        },
        {
          "recipient": 91,
          "score": 58
        },
        {
          "recipient": 104,
          "score": 74
        }
      ]
    },
    "65": {
      "sources": [
        65
      ],
      "dage": 23,
      "matches": [
        {
          "recipient": 12,
          "score": 21
        },
        {
          "recipient": 53,
          "score": 88
        }
      ]
    },
    "66": {
      "sources": [
        66
      ],
      "dage": 52,
      "matches": [
        {
          "recipient": 16,
          "score": 5
        },
        {
          "recipient": 19,
          "score": 24
        },
        {
          "recipient": 25,
          "score": 28
        },
        {
          "recipient": 27,
          "score": 77
        },
        {
          "recipient": 38,
          "score": 15
        },
        {
          "recipient": 40,
          "score": 9
        },
        {
          "recipient": 52,
          "score": 69
        },
        {
          "recipient": 53,
          "score": 0
        },
        {
          "recipient": 54,
          "score": 56
        },
        {
          "recipient": 61,
          "score": 64
        },
        {
          "recipient": 68,
          "score": 66
        },
        {
          "recipient": 71,
          "score": 26
        },
        {
          "recipient": 79,
          "score": 31
        },
        {
          "recipient": 80,
          "score": 9
        },
        {
          "recipient": 89,
          "score": 43
        },
        {
          "recipient": 90,
          "score": 53
        },
        {
          "recipient": 104,
          "score": 59
        },
        {
          "recipient": 105,
          "score": 78
        }
      ]
    },
    "67": {
      "sources": [
        67
      ],
      "dage": 37,
      "matches": [
        {
          "recipient": 12,
          "score": 31
        },
        {
          "recipient": 16,
          "score": 58
        },
        {
          "recipient": 24,
          "score": 9
        },
        {
          "recipient": 27,
          "score": 22
        },
        {
          "recipient": 29,
          "score": 21
        },
        {
          "recipient": 34,
          "score": 42
        },
        {
          "recipient": 38,
          "score": 85
        },
        {
          "recipient": 42,
          "score": 12
        },
        {
          "recipient": 45,
          "score": 61
        },
        {
          "recipient": 49,
          "score": 76
        },
        {
          "recipient": 53,
          "score": 53
        },
        {
          "recipient": 55,
          "score": 57
        },
        {
          "recipient": 61,
          "score": 50
        },
        {
          "recipient": 66,
          "score": 77
        },
        {
          "recipient": 68,
          "score": 12
        },
        {
          "recipient": 71,
          "score": 6
        },
        {
          "recipient": 80,
          "score": 58
        },
        {
          "recipient": 87,
          "score": 78
        },
        {
          "recipient": 89,
          "score": 59
        },
        {
          "recipient": 90,
          "score": 33
        },
        {
          "recipient": 92,
          "score": 60
        },
        {
          "recipient": 99,
          "score": 7
        }
      ]
    },
    "68": {
      "sources": [
        68
      ],
      "dage": 25,
      "matches": [
        {
          "recipient": 36,
          "score": 76
        },
        {
          "recipient": 53,
          "score": 26
        },
        {
          "recipient": 93,
          "score": 4
        }
      ]
    },
    "69": {
      "sources": [
        69
      ],
      "dage": 45,
      "matches": [
        {
          "recipient": 16,
          "score": 19
        },
        {
          "recipient": 23,
          "score": 52
        },
        {
          "recipient": 27,
          "score": 83
        },
        {
          "recipient": 54,
          "score": 16
        },
        {
          "recipient": 61,
          "score": 9
        },
        {
          "recipient": 68,
          "score": 39
        },
        {
          "recipient": 103,
          "score": 78
        },
        {
          "recipient": 104,
          "score": 65
        }
      ]
    },
    "70": {
      "sources": [
        70
      ],
      "dage": 65,
      "matches": [
        {
          "recipient": 16,
          "score": 21
        },
        {
          "recipient": 27,
          "score": 79
        },
        {
          "recipient": 68,
          "score": 70
        },
        {
          "recipient": 104,
          "score": 15
        },
        {
          "recipient": 105,
          "score": 53
        }
      ]
    },
    "71": {
      "sources": [
        71
      ],
      "dage": 61,
      "matches": [
        {
          "recipient": 36,
          "score": 14
        },
        {
          "recipient": 53,
          "score": 54
        }
      ]
    },
    "72": {
      "sources": [
        72
      ],
      "dage": 68,
      "matches": [
        {
          "recipient": 16,
          "score": 82
        },
        {
          "recipient": 20,
          "score": 67
        },
        {
          "recipient": 27,
          "score": 43
        },
        {
          "recipient": 43,
          "score": 52
        },
        {
          "recipient": 61,
          "score": 25
        },
        {
          "recipient": 68,
          "score": 73
        },
        {
          "recipient": 102,
          "score": 36
        },
        {
          "recipient": 104,
          "score": 64
        }
      ]
    },
    "73": {
      "sources": [
        73
      ],
      "dage": 35,
      "matches": [
        {
          "recipient": 12,
          "score": 16
        },
        {
          "recipient": 16,
          "score": 4
        },
        {
          "recipient": 25,
          "score": 65
        },
        {
          "recipient": 27,
          "score": 78
        },
        {
          "recipient": 28,
          "score": 50
        },
        {
          "recipient": 38,
          "score": 7
        },
        {
          "recipient": 43,
          "score": 40
        },
        {
          "recipient": 52,
          "score": 42
        },
        {
          "recipient": 53,
          "score": 7
        },
        {
          "recipient": 59,
          "score": 79
        },
        {
          "recipient": 61,
          "score": 0
        },
        {
          "recipient": 66,
          "score": 14
        },
        {
          "recipient": 68,
          "score": 23
        },
        {
          "recipient": 70,
          "score": 40
        },
        {
          "recipient": 71,
          "score": 62
        },
        {
          "recipient": 77,
          "score": 13
        },
        {
          "recipient": 80,
          "score": 67
        },
        {
          "recipient": 89,
          "score": 14
        },
        {
          "recipient": 90,
          "score": 65
        },
        {
          "recipient": 92,
          "score": 30
        },
        {
          "recipient": 99,
          "score": 38
        }
      ]
    },
    "74": {
      "sources": [
        74
      ],
      "dage": 67,
      "matches": [
        {
          "recipient": 3,
          "score": 19
        },
        {
          "recipient": 16,
          "score": 79
        },
        {
          "recipient": 27,
          "score": 38
        },
        {
          "recipient": 54,
          "score": 79
        },
        {
          "recipient": 61,
          "score": 64
        },
        {
          "recipient": 68,
          "score": 82
        },
        {
          "recipient": 104,
          "score": 79
        }
      ]
    },
    "75": {
      "sources": [
        75
      ],
      "dage": 18,
      "matches": [
        {
          "recipient": 16,
          "score": 86
        },
        {
          "recipient": 24,
          "score": 10
        },
        {
          "recipient": 27,
          "score": 80
        },
        {
          "recipient": 43,
          "score": 70
        },
        {
          "recipient": 61,
          "score": 18
        },
        {
          "recipient": 68,
          "score": 65
        },
        {
          "recipient": 93,
          "score": 63
        },
        {
          "recipient": 104,
          "score": 61
        }
      ]
    },
    "76": {
      "sources": [
        76
      ],
      "dage": 59,
      "matches": [
        {
          "recipient": 6,
          "score": 32
        },
        {
          "recipient": 16,
          "score": 85
        },
        {
          "recipient": 17,
          "score": 52
        },
        {
          "recipient": 21,
          "score": 79
        },
        {
          "recipient": 26,
          "score": 67
        },
        {
          "recipient": 27,
          "score": 17
        },
        {
          "recipient": 29,
          "score": 54
        },
        {
          "recipient": 53,
          "score": 8
        },
        {
          "recipient": 61,
          "score": 83
        },
        {
          "recipient": 63,
          "score": 57
        },
        {
          "recipient": 68,
          "score": 18
        },
        {
          "recipient": 71,
          "score": 16
        },
        {
          "recipient": 89,
          "score": 53
        },
        {
          "recipient": 90,
          "score": 24
        },
        {
          "recipient": 91,
          "score": 41
        },
        {
          "recipient": 94,
          "score": 37
        },
        {
          "recipient": 100,
          "score": 64
        },
        {
          "recipient": 103,
          "score": 2
        },
        {
          "recipient": 104,
          "score": 85
        },
        {
          "recipient": 111,
          "score": 32
        }
      ]
    },
    "77": {
      "sources": [
        77
      ],
      "dage": 67,
      "matches": [
        {
          "recipient": 52,
          "score": 4
        },
        {
          "recipient": 53,
          "score": 5
        }
      ]
    },
    "78": {
      "sources": [
        78
      ],
      "dage": 59,
      "matches": [
        {
          "recipient": 2,
          "score": 49
        },
        {
          "recipient": 3,
          "score": 76
        },
        {
          "recipient": 6,
          "score": 6
        },
        {
          "recipient": 12,
          "score": 83
        },
        {
          "recipient": 18,
          "score": 60
        },
        {
          "recipient": 27,
          "score": 8
        },
        {
          "recipient": 51,
          "score": 48
        },
        {
          "recipient": 61,
          "score": 82
        },
        {
          "recipient": 68,
          "score": 76
        },
        {
          "recipient": 71,
          "score": 59
        },
        {
          "recipient": 76,
          "score": 26
        },
        {
          "recipient": 80,
          "score": 58
        },
        {
          "recipient": 86,
          "score": 71
        },
        {
          "recipient": 89,
          "score": 81
        },
        {
          "recipient": 90,
          "score": 30
        },
        {
          "recipient": 99,
          "score": 77
        },
        {
          "recipient": 104,
          "score": 82
        },
        {
          "recipient": 105,
          "score": 40
        }
      ]
    },
    "79": {
      "sources": [
        79
      ],
      "dage": 44,
      "matches": [
        {
          "recipient": 50,
          "score": 36
        },
        {
          "recipient": 53,
          "score": 57
        }
      ]
    },
    "80": {
      "sources": [
        80
      ],
      "dage": 60,
      "matches": [
        {
          "recipient": 8,
          "score": 66
        },
        {
          "recipient": 16,
          "score": 58
        },
        {
          "recipient": 27,
          "score": 10
        },
        {
          "recipient": 54,
          "score": 74
        },
        {
          "recipient": 61,
          "score": 56
        },
        {
          "recipient": 68,
          "score": 60
        },
        {
          "recipient": 104,
          "score": 53
        },
        {
          "recipient": 105,
          "score": 26
        },
        {
          "recipient": 106,
          "score": 50
        }
      ]
    },
    "81": {
      "sources": [
        81
      ],
      "dage": 54,
      "matches": [
        {
          "recipient": 1,
          "score": 81
        },
        {
          "recipient": 16,
          "score": 47
        },
        {
          "recipient": 27,
          "score": 39
        },
        {
          "recipient": 61,
          "score": 11
        },
        {
          "recipient": 68,
          "score": 21
        },
        {
          "recipient": 104,
          "score": 68
        },
        {
          "recipient": 105,
          "score": 66
        }
      ]
    },
    "82": {
      "sources": [
        82
      ],
      "dage": 51,
      "matches": [
        {
          "recipient": 16,
          "score": 44
        },
        {
          "recipient": 26,
          "score": 35
        },
        {
          "recipient": 27,
          "score": 59
        },
        {
          "recipient": 28,
          "score": 74
        },
        {
          "recipient": 37,
          "score": 75
        },
        {
          "recipient": 61,
          "score": 21
        },
        {
          "recipient": 68,
          "score": 65
        },
        {
          "recipient": 93,
          "score": 86
        }
      ]
    },
    "83": {
      "sources": [
        83
      ],
      "dage": 37,
      "matches": [
        {
          "recipient": 16,
          "score": 38
        },
        {
          "recipient": 27,
          "score": 16
        },
        {
          "recipient": 33,
          "score": 27
        },
        {
          "recipient": 38,
          "score": 4
        },
        {
          "recipient": 53,
          "score": 60
        },
        {
          "recipient": 58,
          "score": 77
        },
        {
          "recipient": 68,
          "score": 60
        },
        {
          "recipient": 71,
          "score": 13
        },
        {
          "recipient": 80,
          "score": 38
        },
        {
          "recipient": 89,
          "score": 75
        },
        {
          "recipient": 90,
          "score": 81
        },
        {
          "recipient": 94,
          "score": 82
        },
        {
          "recipient": 97,
          "score": 42
        },
        {
          "recipient": 104,
          "score": 69
        }
      ]
    },
    "84": {
      "sources": [
        84
      ],
      "dage": 21,
      "matches": [
        {
          "recipient": 16,
          "score": 37
        },
        {
          "recipient": 27,
          "score": 68
        },
        {
          "recipient": 68,
          "score": 68
        },
        {
          "recipient": 79,
          "score": 82
        },
        {
          "recipient": 104,
          "score": 44
        }
      ]
    },
    "86": {
      "sources": [
        86
      ],
      "dage": 45,
      "matches": [
        {
          "recipient": 53,
          "score": 72
        },
        {
          "recipient": 102,
          "score": 4
        }
      ]
    },
    "87": {
      "sources": [
        87
      ],
      "dage": 45,
      "matches": [
        {
          "recipient": 16,
          "score": 87
        },
        {
          "recipient": 20,
          "score": 37
        },
        {
          "recipient": 27,
          "score": 3
        },
        {
          "recipient": 28,
          "score": 79
        },
        {
          "recipient": 29,
          "score": 0
        },
        {
          "recipient": 38,
          "score": 62
        },
        {
          "recipient": 51,
          "score": 42
        },
        {
          "recipient": 56,
          "score": 38
        },
        {
          "recipient": 61,
          "score": 87
        },
        {
          "recipient": 68,
          "score": 26
        },
        {
          "recipient": 71,
          "score": 78
        },
        {
          "recipient": 73,
          "score": 16
        },
        {
          "recipient": 80,
          "score": 27
        },
        {
          "recipient": 83,
          "score": 17
        },
        {
          "recipient": 90,
          "score": 2
        },
        {
          "recipient": 91,
          "score": 83
        },
        {
          "recipient": 92,
          "score": 33
        },
        {
          "recipient": 101,
          "score": 43
        },
        {
          "recipient": 103,
          "score": 80
        },
        {
          "recipient": 104,
          "score": 15
        },
        {
          "recipient": 111,
          "score": 16
        }
      ]
    },
    "88": {
      "sources": [
        88
      ],
      "dage": 36
    },
    "89": {
      "sources": [
        89
      ],
      "dage": 67,
      "matches": [
        {
          "recipient": 27,
          "score": 20
        },
        {
          "recipient": 37,
          "score": 67
        },
        {
          "recipient": 61,
          "score": 34
        },
        {
          "recipient": 68,
          "score": 33
        },
        {
          "recipient": 92,
          "score": 54
        },
        {
          "recipient": 104,
          "score": 81
        }
      ]
    },
    "90": {
      "sources": [
        90
      ],
      "dage": 65
    },
    "91": {
      "sources": [
        91
      ],
      "dage": 67,
      "matches": [
        {
          "recipient": 18,
          "score": 31
        },
        {
          "recipient": 36,
          "score": 87
        },
        {
          "recipient": 53,
          "score": 37
        }
      ]
    },
    "92": {
      "sources": [
        92
      ],
      "dage": 29,
      "matches": [
        {
          "recipient": 53,
          "score": 72
        },
        {
          "recipient": 93,
          "score": 74
        },
        {
          "recipient": 102,
          "score": 25
        }
      ]
    },
    "93": {
      "sources": [
        93
      ],
      "dage": 30,
      "matches": [
        {
          "recipient": 16,
          "score": 33
        },
        {
          "recipient": 26,
          "score": 64
        },
        {
          "recipient": 27,
          "score": 46
        },
        {
          "recipient": 36,
          "score": 27
        },
        {
          "recipient": 38,
          "score": 47
        },
        {
          "recipient": 40,
          "score": 68
        },
        {
          "recipient": 45,
          "score": 79
        },
        {
          "recipient": 49,
          "score": 63
        },
        {
          "recipient": 51,
          "score": 76
        },
        {
          "recipient": 53,
          "score": 67
        },
        {
          "recipient": 56,
          "score": 13
        },
        {
          "recipient": 61,
          "score": 15
        },
        {
          "recipient": 77,
          "score": 76
        },
        {
          "recipient": 81,
          "score": 34
        },
        {
          "recipient": 88,
          "score": 62
        },
        {
          "recipient": 89,
          "score": 9
        },
        {
          "recipient": 90,
          "score": 44
        },
        {
          "recipient": 95,
          "score": 20
        },
        {
          "recipient": 104,
          "score": 52
        },
        {
          "recipient": 110,
          "score": 14
        }
      ]
    },
    "94": {
      "sources": [
        94
      ],
      "dage": 38,
      "matches": [
        {
          "recipient": 1,
          "score": 59
        },
        {
          "recipient": 16,
          "score": 89
        },
        {
          "recipient": 27,
          "score": 52
        },
        {
          "recipient": 28,
          "score": 71
        },
        {
          "recipient": 31,
          "score": 59
        },
        {
          "recipient": 34,
          "score": 39
        },
        {
          "recipient": 38,
          "score": 87
        },
        {
          "recipient": 53,
          "score": 40
        },
        {
          "recipient": 56,
          "score": 31
        },
        {
          "recipient": 61,
          "score": 9
        },
        {
          "recipient": 65,
          "score": 4
        },
        {
          "recipient": 68,
          "score": 65
        },
        {
          "recipient": 71,
          "score": 5
        },
        {
          "recipient": 80,
          "score": 49
        },
        {
          "recipient": 81,
          "score": 6
        },
        {
          "recipient": 82,
          "score": 2
        },
        {
          "recipient": 84,
          "score": 23
        },
        {
          "recipient": 89,
          "score": 70
        },
        {
          "recipient": 90,
          "score": 57
        },
        {
          "recipient": 104,
          "score": 46
        }
      ]
    },
    "95": {
      "sources": [
        95
      ],
      "dage": 34,
      "matches": [
        {
          "recipient": 16,
          "score": 59
        },
        {
          "recipient": 27,
          "score": 73
        },
        {
          "recipient": 61,
          "score": 22
        },
        {
          "recipient": 68,
          "score": 8
        },
        {
          "recipient": 104,
          "score": 39
        }
      ]
    },
    "96": {
      "sources": [
        96
      ],
      "dage": 49,
      "matches": [
        {
          "recipient": 7,
          "score": 35
        },
        {
          "recipient": 16,
          "score": 67
        },
        {
          "recipient": 20,
          "score": 48
        },
        {
          "recipient": 29,
          "score": 56
        },
        {
          "recipient": 38,
          "score": 17
        },
        {
          "recipient": 40,
          "score": 22
        },
        {
          "recipient": 43,
          "score": 53
        },
        {
          "recipient": 45,
          "score": 30
        },
        {
          "recipient": 53,
          "score": 11
        },
        {
          "recipient": 68,
          "score": 48
        },
        {
          "recipient": 71,
          "score": 44
        },
        {
          "recipient": 72,
          "score": 28
        },
        {
          "recipient": 83,
          "score": 15
        },
        {
          "recipient": 89,
          "score": 71
        },
        {
          "recipient": 90,
          "score": 88
        },
        {
          "recipient": 104,
          "score": 56
        },
        {
          "recipient": 106,
          "score": 55
        }
      ]
    },
    "97": {
      "sources": [
        97
      ],
      "dage": 47,
      "matches": [
        {
          "recipient": 5,
          "score": 50
        },
        {
          "recipient": 9,
          "score": 43
        },
        {
          "recipient": 14,
          "score": 50
        },
        {
          "recipient": 16,
          "score": 77
        },
        {
          "recipient": 21,
          "score": 22
        },
        {
          "recipient": 25,
          "score": 75
        },
        {
          "recipient": 27,
          "score": 12
        },
        {
          "recipient": 38,
          "score": 9
        },
        {
          "recipient": 40,
          "score": 35
        },
        {
          "recipient": 44,
          "score": 53
        },
        {
          "recipient": 48,
          "score": 89
        },
        {
          "recipient": 49,
          "score": 39
        },
        {
          "recipient": 53,
          "score": 80
        },
        {
          "recipient": 68,
          "score": 71
        },
        {
          "recipient": 71,
          "score": 61
        },
        {
          "recipient": 73,
          "score": 34
        },
        {
          "recipient": 76,
          "score": 7
        },
        {
          "recipient": 77,
          "score": 46
        },
        {
          "recipient": 80,
          "score": 86
        },
        {
          "recipient": 89,
          "score": 13
        },
        {
          "recipient": 90,
          "score": 69
        },
        {
          "recipient": 104,
          "score": 26
        },
        {
          "recipient": 106,
          "score": 88
        }
      ]
    },
    "99": {
      "sources": [
        99
      ],
      "dage": 25,
      "matches": [
        {
          "recipient": 12,
          "score": 53
        },
        {
          "recipient": 53,
          "score": 23
        },
        {
          "recipient": 91,
          "score": 72
        }
      ]
    },
    "100": {
      "sources": [
        100
      ],
      "dage": 54,
      "matches": [
        {
          "recipient": 16,
          "score": 7
        },
        {
          "recipient": 24,
          "score": 34
        },
        {
          "recipient": 27,
          "score": 37
        },
        {
          "recipient": 46,
          "score": 44
        },
        {
          "recipient": 53,
          "score": 76
        },
        {
          "recipient": 57,
          "score": 17
        },
        {
          "recipient": 61,
          "score": 35
        },
        {
          "recipient": 62,
          "score": 34
        },
        {
          "recipient": 68,
          "score": 48
        },
        {
          "recipient": 70,
          "score": 13
        },
        {
          "recipient": 71,
          "score": 65
        },
        {
          "recipient": 77,
          "score": 24
        },
        {
          "recipient": 78,
          "score": 66
        },
        {
          "recipient": 82,
          "score": 80
        },
        {
          "recipient": 89,
          "score": 68
        },
        {
          "recipient": 90,
          "score": 31
        },
        {
          "recipient": 91,
          "score": 62
        },
        {
          "recipient": 92,
          "score": 69
        },
        {
          "recipient": 101,
          "score": 63
        },
        {
          "recipient": 104,
          "score": 75
        }
      ]
    },
    "101": {
      "sources": [
        101
      ],
      "dage": 50,
      "matches": [
        {
          "recipient": 16,
          "score": 51
        },
        {
          "recipient": 27,
          "score": 82
        },
        {
          "recipient": 61,
          "score": 68
        },
        {
          "recipient": 68,
          "score": 58
        },
        {
          "recipient": 104,
          "score": 14
        }
      ]
    },
    "102": {
      "sources": [
        102
      ],
      "dage": 36,
      "matches": [
        {
          "recipient": 1,
          "score": 69
        },
        {
          "recipient": 16,
          "score": 10
        },
        {
          "recipient": 24,
          "score": 32
        },
        {
          "recipient": 27,
          "score": 37
        },
        {
          "recipient": 37,
          "score": 32
        },
        {
          "recipient": 54,
          "score": 5
        },
        {
          "recipient": 61,
          "score": 65
        },
        {
          "recipient": 68,
          "score": 70
        },
        {
          "recipient": 77,
          "score": 74
        },
        {
          "recipient": 92,
          "score": 86
        },
        {
          "recipient": 104,
          "score": 14
        }
      ]
    },
    "103": {
      "sources": [
        103
      ],
      "dage": 33,
      "matches": [
        {
          "recipient": 9,
          "score": 60
        },
        {
          "recipient": 16,
          "score": 12
        },
        {
          "recipient": 18,
          "score": 28
        },
        {
          "recipient": 23,
          "score": 33
        },
        {
          "recipient": 27,
          "score": 36
        },
        {
          "recipient": 29,
          "score": 51
        },
        {
          "recipient": 31,
          "score": 70
        },
        {
          "recipient": 38,
          "score": 39
        },
        {
          "recipient": 50,
          "score": 81
        },
        {
          "recipient": 53,
          "score": 5
        },
        {
          "recipient": 61,
          "score": 2
        },
        {
          "recipient": 68,
          "score": 33
        },
        {
          "recipient": 69,
          "score": 66
        },
        {
          "recipient": 71,
          "score": 85
        },
        {
          "recipient": 80,
          "score": 45
        },
        {
          "recipient": 90,
          "score": 43
        },
        {
          "recipient": 100,
          "score": 16
        },
        {
          "recipient": 104,
          "score": 62
        },
        {
          "recipient": 110,
          "score": 51
        }
      ]
    },
    "104": {
      "sources": [
        104
      ],
      "dage": 36
    },
    "105": {
      "sources": [
        105
      ],
      "dage": 35,
      "matches": [
        {
          "recipient": 16,
          "score": 79
        },
        {
          "recipient": 27,
          "score": 11
        },
        {
          "recipient": 61,
          "score": 64
        },
        {
          "recipient": 68,
          "score": 40
        },
        {
          "recipient": 104,
          "score": 59
        }
      ]
    },
    "106": {
      "sources": [
        106
      ],
      "dage": 25,
      "matches": [
        {
          "recipient": 2,
          "score": 13
        },
        {
          "recipient": 38,
          "score": 71
        },
        {
          "recipient": 42,
          "score": 6
        },
        {
          "recipient": 52,
          "score": 25
        },
        {
          "recipient": 61,
          "score": 44
        },
        {
          "recipient": 65,
          "score": 38
        },
        {
          "recipient": 68,
          "score": 6
        },
        {
          "recipient": 80,
          "score": 24
        },
        {
          "recipient": 89,
          "score": 6
        },
        {
          "recipient": 104,
          "score": 46
        }
      ]
    },
    "108": {
      "sources": [
        108
      ],
      "dage": 36,
      "matches": [
        {
          "recipient": 2,
          "score": 5
        },
        {
          "recipient": 16,
          "score": 44
        },
        {
          "recipient": 24,
          "score": 60
        },
        {
          "recipient": 25,
          "score": 30
        },
        {
          "recipient": 27,
          "score": 75
        },
        {
          "recipient": 34,
          "score": 37
        },
        {
          "recipient": 38,
          "score": 59
        },
        {
          "recipient": 53,
          "score": 0
        },
        {
          "recipient": 61,
          "score": 77
        },
        {
          "recipient": 68,
          "score": 42
        },
        {
          "recipient": 71,
          "score": 21
        },
        {
          "recipient": 80,
          "score": 24
        },
        {
          "recipient": 89,
          "score": 87
        },
        {
          "recipient": 90,
          "score": 76
        },
        {
          "recipient": 96,
          "score": 41
        },
        {
          "recipient": 104,
          "score": 26
        }
      ]
    },
    "109": {
      "sources": [
        109
      ],
      "dage": 56,
      "matches": [
        {
          "recipient": 16,
          "score": 15
        },
        {
          "recipient": 27,
          "score": 47
        },
        {
          "recipient": 38,
          "score": 75
        },
        {
          "recipient": 40,
          "score": 14
        },
        {
          "recipient": 51,
          "score": 77
        },
        {
          "recipient": 52,
          "score": 64
        },
        {
          "recipient": 53,
          "score": 35
        },
        {
          "recipient": 55,
          "score": 65
        },
        {
          "recipient": 61,
          "score": 43
        },
        {
          "recipient": 71,
          "score": 65
        },
        {
          "recipient": 80,
          "score": 50
        },
        {
          "recipient": 89,
          "score": 33
        },
        {
          "recipient": 90,
          "score": 47
        }
      ]
    },
    "110": {
      "sources": [
        110
      ],
      "dage": 32,
      "matches": [
        {
          "recipient": 3,
          "score": 82
        },
        {
          "recipient": 16,
          "score": 79
        },
        {
          "recipient": 27,
          "score": 58
        },
        {
          "recipient": 61,
          "score": 72
        },
        {
          "recipient": 68,
          "score": 3
        },
        {
          "recipient": 102,
          "score": 2
        },
        {
          "recipient": 104,
          "score": 66
        }
      ]
    },
    "111": {
      "sources": [
        111
      ],
      "dage": 35,
      "matches": [
        {
          "recipient": 16,
          "score": 33
        },
        {
          "recipient": 24,
          "score": 57
        },
        {
          "recipient": 27,
          "score": 22
        },
        {
          "recipient": 61,
          "score": 28
        },
        {
          "recipient": 68,
          "score": 72
        },
        {
          "recipient": 104,
          "score": 79
        },
        {
          "recipient": 106,
          "score": 64
        }
      ]
    }
  }
}